Metadata-Version: 2.1
Name: pylocale
Version: 0.0.1
Summary: A Python3 library without dependencies that provides static translations across your app
Home-page: https://github.com/mavedev/pylocale
Author: Cirill Usachov (Kyrylo Usachov)
Author-email: mave7dev@gmail.com
License: UNKNOWN
Platform: UNKNOWN
Classifier: Programming Language :: Python :: 3
Classifier: License :: OSI Approved :: MIT License
Classifier: Operating System :: OS Independent
Requires-Python: >=3.6
